Metadata-Version: 1.0
Name: BFClust
Version: 0.1.26.1
Summary: Boundary Forest Clustering
Home-page: https://github.com/dsurujon/BFClust-python
Author: Defne Surujon
Author-email: defnesurujon@gmail.com
License: UNKNOWN
Platform: UNKNOWN
